elementMass/Periodic_table.py
elementMass/__init__.py
elementMass/elements.py
elementMass/oxidation_states.py
elementMass/data/__init__.py
elementMass/data/periodic_table.parquet
elementMass-1.1.0.dist-info/LICENSE
elementMass-1.1.0.dist-info/METADATA
elementMass-1.1.0.dist-info/WHEEL
elementMass-1.1.0.dist-info/top_level.txt
elementMass-1.1.0.dist-info/RECORD
