Metadata-Version: 2.2
Name: elementMass
Version: 1.1.0
Summary: elementMass is a compact Python library for calculating atomic weights of chemical compounds
Author: Thomas van Gerve
License: MIT License
Project-URL: Homepage, https://github.com/TDGerve/elements
Classifier: Programming Language :: Python :: 3
Classifier: License :: OSI Approved :: MIT License
Classifier: Operating System :: OS Independent
Requires-Python: >=3.8
License-File: LICENSE
Requires-Dist: pandas
Requires-Dist: pyarrow
